py_ecc/__init__.py
py_ecc/py.typed
py_ecc/typing.py
py_ecc/utils.py
py_ecc/bls/__init__.py
py_ecc/bls/ciphersuites.py
py_ecc/bls/constants.py
py_ecc/bls/g2_primitives.py
py_ecc/bls/hash.py
py_ecc/bls/hash_to_curve.py
py_ecc/bls/point_compression.py
py_ecc/bls/typing.py
py_ecc/bls12_381/__init__.py
py_ecc/bls12_381/bls12_381_curve.py
py_ecc/bls12_381/bls12_381_pairing.py
py_ecc/bn128/__init__.py
py_ecc/bn128/bn128_curve.py
py_ecc/bn128/bn128_pairing.py
py_ecc/fields/__init__.py
py_ecc/fields/field_elements.py
py_ecc/fields/field_properties.py
py_ecc/fields/optimized_field_elements.py
py_ecc/optimized_bls12_381/__init__.py
py_ecc/optimized_bls12_381/constants.py
py_ecc/optimized_bls12_381/optimized_clear_cofactor.py
py_ecc/optimized_bls12_381/optimized_curve.py
py_ecc/optimized_bls12_381/optimized_pairing.py
py_ecc/optimized_bls12_381/optimized_swu.py
py_ecc/optimized_bn128/__init__.py
py_ecc/optimized_bn128/optimized_curve.py
py_ecc/optimized_bn128/optimized_pairing.py
py_ecc/secp256k1/__init__.py
py_ecc/secp256k1/secp256k1.py
py_ecc-7.0.1.dist-info/LICENSE
py_ecc-7.0.1.dist-info/METADATA
py_ecc-7.0.1.dist-info/WHEEL
py_ecc-7.0.1.dist-info/top_level.txt
py_ecc-7.0.1.dist-info/RECORD
