Metadata-Version: 2.1
Name: py-ecc
Version: 7.0.1
Summary: py-ecc: Elliptic curve crypto in python including secp256k1, alt_bn128, and bls12_381
Home-page: https://github.com/ethereum/py_ecc
Author: The Ethereum Foundation
Author-email: snakecharmers@ethereum.org
License: MIT
Keywords: ethereum
Classifier: Development Status :: 3 - Alpha
Classifier: Intended Audience :: Developers
Classifier: License :: OSI Approved :: MIT License
Classifier: Natural Language :: English
Classifier: Programming Language :: Python :: 3
Classifier: Programming Language :: Python :: 3.8
Classifier: Programming Language :: Python :: 3.9
Classifier: Programming Language :: Python :: 3.10
Classifier: Programming Language :: Python :: 3.11
Classifier: Programming Language :: Python :: 3.12
Requires-Python: >=3.8, <4
License-File: LICENSE
Requires-Dist: eth-typing>=3.0.0
Requires-Dist: eth-utils>=2.0.0
Requires-Dist: cached-property>=1.5.1
Provides-Extra: dev
Requires-Dist: build>=0.9.0; extra == "dev"
Requires-Dist: bumpversion>=0.5.3; extra == "dev"
Requires-Dist: ipython; extra == "dev"
Requires-Dist: pre-commit>=3.4.0; extra == "dev"
Requires-Dist: tox>=4.0.0; extra == "dev"
Requires-Dist: twine; extra == "dev"
Requires-Dist: wheel; extra == "dev"
Requires-Dist: sphinx>=6.0.0; extra == "dev"
Requires-Dist: sphinx-autobuild>=2021.3.14; extra == "dev"
Requires-Dist: sphinx_rtd_theme>=1.0.0; extra == "dev"
Requires-Dist: towncrier<22,>=21; extra == "dev"
Requires-Dist: pytest>=7.0.0; extra == "dev"
Requires-Dist: pytest-xdist>=2.4.0; extra == "dev"
Provides-Extra: docs
Requires-Dist: sphinx>=6.0.0; extra == "docs"
Requires-Dist: sphinx-autobuild>=2021.3.14; extra == "docs"
Requires-Dist: sphinx_rtd_theme>=1.0.0; extra == "docs"
Requires-Dist: towncrier<22,>=21; extra == "docs"
Provides-Extra: test
Requires-Dist: pytest>=7.0.0; extra == "test"
Requires-Dist: pytest-xdist>=2.4.0; extra == "test"
